aurelis/__init__.py
aurelis/bin/__init__.py
aurelis/bin/aurelis.py
aurelis/cli/__init__.py
aurelis/cli/main.py
aurelis/core/__init__.py
aurelis/core/ai.py
aurelis/core/database.py
aurelis/core/file.py
aurelis/core/internet.py
aurelis/core/reasoner.py
aurelis/core/services.py
aurelis/utils/__init__.py
aurelis/utils/ascii_art.py
aurelis/utils/code_utils.py
aurelis/utils/config.py
aurelis/utils/testing.py
aurelis-1.0.1.dist-info/LICENSE
aurelis-1.0.1.dist-info/METADATA
aurelis-1.0.1.dist-info/WHEEL
aurelis-1.0.1.dist-info/entry_points.txt
aurelis-1.0.1.dist-info/top_level.txt
aurelis-1.0.1.dist-info/RECORD
