Metadata-Version: 2.2
Name: aurelis
Version: 1.0.1
Summary: AI-powered coding assistant with advanced reasoning capabilities
Home-page: https://github.com/Kanopusdev/aurelis
Author: Pradyumn Tandon
Author-email: pradyumn.tandon@hotmail.com
Classifier: Development Status :: 4 - Beta
Classifier: Intended Audience :: Developers
Classifier: License :: OSI Approved :: MIT License
Classifier: Operating System :: OS Independent
Classifier: Programming Language :: Python :: 3.8
Classifier: Programming Language :: Python :: 3.9
Classifier: Programming Language :: Python :: 3.10
Requires-Python: >=3.8
License-File: LICENSE
Requires-Dist: click
Requires-Dist: rich
Requires-Dist: python-dotenv
Requires-Dist: faiss-cpu
Requires-Dist: numpy
Requires-Dist: requests
Requires-Dist: aiohttp
Requires-Dist: asyncio
Requires-Dist: duckduckgo-search
Requires-Dist: azure-ai-inference
Requires-Dist: scipy
Requires-Dist: pyperclip
Requires-Dist: pytest
Requires-Dist: pylint
Requires-Dist: pathlib
Requires-Dist: typing
Requires-Dist: black
Requires-Dist: isort
Requires-Dist: mypy
Requires-Dist: pytest-asyncio
Requires-Dist: pytest-cov
Dynamic: author
Dynamic: author-email
Dynamic: classifier
Dynamic: description
Dynamic: description-content-type
Dynamic: home-page
Dynamic: requires-dist
Dynamic: requires-python
Dynamic: summary
